edastatmil_milser/__init__.py
edastatmil_milser/commandline.py
edastatmil_milser/edas_tatmil.py
edastatmil_milser/version.py
edastatmil_milser-0.16.dist-info/LICENSE
edastatmil_milser-0.16.dist-info/METADATA
edastatmil_milser-0.16.dist-info/WHEEL
edastatmil_milser-0.16.dist-info/top_level.txt
edastatmil_milser-0.16.dist-info/RECORD
