Metadata-Version: 2.1
Name: edastatmil_milser
Version: 0.16
Summary: A small example package
Home-page: https://github.com/milser/edas_tatianamilser
Author: Tatiana Cazorla y Rubén Serrano
Author-email: TatianaCC y milser <author@example.com>
Project-URL: Homepage, https://github.com/milser/edas_tatianamilser
Project-URL: Issues, https://github.com/milser/edas_tatianamilser/issues
Classifier: Programming Language :: Python :: 3
Classifier: License :: OSI Approved :: MIT License
Classifier: Operating System :: OS Independent
Requires-Python: >=3.8
License-File: LICENSE
